Metadata-Version: 2.1
Name: madhava
Version: 0.0.1
Summary: Madhava Formular to find π 
Home-page: 
Download-URL: https://github.com/SaranphatRoungkitrakran/madhavapi/releases/tag/0.0.1
Author: Saranphat Roungkitrakran
Author-email: Gungungungundam@hotmail.com
License: MIT
Keywords: MADHAVA,PI,MADHAVAPI,CIRCLE
Classifier: Development Status :: 3 - Alpha
Classifier: Intended Audience :: Developers
Classifier: Topic :: Software Development :: Build Tools
Classifier: License :: OSI Approved :: MIT License
Classifier: Programming Language :: Python :: 3
Classifier: Programming Language :: Python :: 3.4
Classifier: Programming Language :: Python :: 3.5
Classifier: Programming Language :: Python :: 3.6
Classifier: Programming Language :: Python :: 3.7
Classifier: Programming Language :: Python :: 3.8
Classifier: Programming Language :: Python :: 3.9
License-File: LICENSE.txt
